{"cameraMode":{"drawMode":0,"name":"Shaded","section":"Shading Mode"},"sceneLighting":true,"audioPlay":false,"sceneViewState":{"showFog":true,"showMaterialUpdate":false,"showSkybox":false,"showFlares":true,"showImageEffects":true,"showParticleSystems":true,"showVisualEffectGraphs":true,"m_FxEnabled":true},"in2DMode":false,"pivot":{"x":319.0,"y":722.0,"z":-575.0},"rotation":{"x":0.2949398159980774,"y":-0.005733051802963018,"z":0.0017696599243208767,"w":0.9554970860481262},"size":386.8085632324219,"orthographic":true}